ip2location_timezone/__init__.py
ip2location_timezone/middleware.py
ip2location_timezone/urls.py
ip2location_timezone/views.py
django_ip2location_timezone-1.0.0.dist-info/AUTHORS
django_ip2location_timezone-1.0.0.dist-info/LICENSE.TXT
django_ip2location_timezone-1.0.0.dist-info/METADATA
django_ip2location_timezone-1.0.0.dist-info/WHEEL
django_ip2location_timezone-1.0.0.dist-info/top_level.txt
django_ip2location_timezone-1.0.0.dist-info/RECORD
