Metadata-Version: 2.1
Name: django-ip2location-timezone
Version: 1.0.0
Summary: Django IP2Location Timezone is a simple Django package that can help you easily display your website visitor the time according to their location.
Home-page: https://github.com/ip2location/django-ip2location-timezone
Author: IP2Location
Author-email: support@ip2location.com
License: MIT License
Platform: UNKNOWN
Classifier: Environment :: Web Environment
Classifier: Framework :: Django
Classifier: Framework :: Django :: 1.11
Classifier: Framework :: Django :: 2.2
Classifier: Intended Audience :: Developers
Classifier: License :: OSI Approved :: MIT License
Classifier: Operating System :: OS Independent
Classifier: Programming Language :: Python
Classifier: Programming Language :: Python :: 2.7
Classifier: Programming Language :: Python :: 3
Classifier: Topic :: Internet :: WWW/HTTP
Classifier: Topic :: Internet :: WWW/HTTP :: Dynamic Content
